[
  {
    "title": "前言",
    "slug": "readme",
    "depth": 1
  },
  {
    "title": "修订记录",
    "slug": "changelog",
    "depth": 1
  },
  {
    "title": "如何贡献",
    "slug": "contributing",
    "depth": 1
  },
  {
    "title": "Docker 简介",
    "slug": "introduction_readme",
    "depth": 1
  },
  {
    "title": "什么是 Docker",
    "slug": "introduction_what",
    "depth": 2
  },
  {
    "title": "为什么要用 Docker",
    "slug": "introduction_why",
    "depth": 2
  },
  {
    "title": "基本概念",
    "slug": "basic_concept_readme",
    "depth": 1
  },
  {
    "title": "镜像",
    "slug": "basic_concept_image",
    "depth": 2
  },
  {
    "title": "容器",
    "slug": "basic_concept_container",
    "depth": 2
  },
  {
    "title": "仓库",
    "slug": "basic_concept_repository",
    "depth": 2
  },
  {
    "title": "安装 Docker",
    "slug": "install_readme",
    "depth": 1
  },
  {
    "title": "Ubuntu",
    "slug": "install_ubuntu",
    "depth": 2
  },
  {
    "title": "Debian",
    "slug": "install_debian",
    "depth": 2
  },
  {
    "title": "Fedora",
    "slug": "install_fedora",
    "depth": 2
  },
  {
    "title": "CentOS",
    "slug": "install_centos",
    "depth": 2
  },
  {
    "title": "Raspberry Pi",
    "slug": "install_raspberry-pi",
    "depth": 2
  },
  {
    "title": "macOS",
    "slug": "install_mac",
    "depth": 2
  },
  {
    "title": "Windows 10",
    "slug": "install_windows",
    "depth": 2
  },
  {
    "title": "镜像加速器",
    "slug": "install_mirror",
    "depth": 2
  },
  {
    "title": "开启实验特性",
    "slug": "install_experimental",
    "depth": 2
  },
  {
    "title": "使用镜像",
    "slug": "image_readme",
    "depth": 1
  },
  {
    "title": "获取镜像",
    "slug": "image_pull",
    "depth": 2
  },
  {
    "title": "列出镜像",
    "slug": "image_list",
    "depth": 2
  },
  {
    "title": "删除本地镜像",
    "slug": "image_rm",
    "depth": 2
  },
  {
    "title": "利用 commit 理解镜像构成",
    "slug": "image_commit",
    "depth": 2
  },
  {
    "title": "使用 Dockerfile 定制镜像",
    "slug": "image_build",
    "depth": 2
  },
  {
    "title": "Dockerfile 指令详解",
    "slug": "image_dockerfile_readme",
    "depth": 2
  },
  {
    "title": "COPY 复制文件",
    "slug": "image_dockerfile_copy",
    "depth": 3
  },
  {
    "title": "ADD 更高级的复制文件",
    "slug": "image_dockerfile_add",
    "depth": 3
  },
  {
    "title": "CMD 容器启动命令",
    "slug": "image_dockerfile_cmd",
    "depth": 3
  },
  {
    "title": "ENTRYPOINT 入口点",
    "slug": "image_dockerfile_entrypoint",
    "depth": 3
  },
  {
    "title": "ENV 设置环境变量",
    "slug": "image_dockerfile_env",
    "depth": 3
  },
  {
    "title": "ARG 构建参数",
    "slug": "image_dockerfile_arg",
    "depth": 3
  },
  {
    "title": "VOLUME 定义匿名卷",
    "slug": "image_dockerfile_volume",
    "depth": 3
  },
  {
    "title": "EXPOSE 暴露端口",
    "slug": "image_dockerfile_expose",
    "depth": 3
  },
  {
    "title": "WORKDIR 指定工作目录",
    "slug": "image_dockerfile_workdir",
    "depth": 3
  },
  {
    "title": "USER 指定当前用户",
    "slug": "image_dockerfile_user",
    "depth": 3
  },
  {
    "title": "HEALTHCHECK 健康检查",
    "slug": "image_dockerfile_healthcheck",
    "depth": 3
  },
  {
    "title": "ONBUILD 为他人作嫁衣裳",
    "slug": "image_dockerfile_onbuild",
    "depth": 3
  },
  {
    "title": "参考文档",
    "slug": "image_dockerfile_references",
    "depth": 3
  },
  {
    "title": "Dockerfile 多阶段构建",
    "slug": "image_multistage-builds_readme",
    "depth": 2
  },
  {
    "title": "实战多阶段构建 Laravel 镜像",
    "slug": "image_multistage-builds_laravel",
    "depth": 3
  },
  {
    "title": "构建多种系统架构支持的 Docker 镜像",
    "slug": "image_manifest",
    "depth": 2
  },
  {
    "title": "其它制作镜像的方式",
    "slug": "image_other",
    "depth": 2
  },
  {
    "title": "实现原理",
    "slug": "image_internal",
    "depth": 2
  },
  {
    "title": "操作容器",
    "slug": "container_readme",
    "depth": 1
  },
  {
    "title": "增删改查",
    "slug": "at7zi0",
    "depth": 2
  },
  {
    "title": "启动",
    "slug": "container_run",
    "depth": 2
  },
  {
    "title": "守护态运行",
    "slug": "container_daemon",
    "depth": 2
  },
  {
    "title": "终止&重启",
    "slug": "container_stop",
    "depth": 2
  },
  {
    "title": "进入容器",
    "slug": "container_attach_exec",
    "depth": 2
  },
  {
    "title": "导出和导入",
    "slug": "container_import_export",
    "depth": 2
  },
  {
    "title": "删除",
    "slug": "container_rm",
    "depth": 2
  },
  {
    "title": "访问仓库",
    "slug": "repository_readme",
    "depth": 1
  },
  {
    "title": "Docker Hub",
    "slug": "repository_dockerhub",
    "depth": 2
  },
  {
    "title": "私有仓库",
    "slug": "repository_registry",
    "depth": 2
  },
  {
    "title": "私有仓库高级配置",
    "slug": "repository_registry_auth",
    "depth": 2
  },
  {
    "title": "Nexus 3",
    "slug": "repository_nexus3_registry",
    "depth": 2
  },
  {
    "title": "数据管理",
    "slug": "data_management_readme",
    "depth": 1
  },
  {
    "title": "文件互传",
    "slug": "rdoxdu",
    "depth": 2
  },
  {
    "title": "数据卷",
    "slug": "data_management_volume",
    "depth": 2
  },
  {
    "title": "挂载主机目录",
    "slug": "data_management_bind-mounts",
    "depth": 2
  },
  {
    "title": "使用网络",
    "slug": "network_readme",
    "depth": 1
  },
  {
    "title": "外部访问容器",
    "slug": "network_port_mapping",
    "depth": 2
  },
  {
    "title": "容器互联",
    "slug": "network_linking",
    "depth": 2
  },
  {
    "title": "配置 DNS",
    "slug": "network_dns",
    "depth": 2
  },
  {
    "title": "高级网络配置",
    "slug": "advanced_network_readme",
    "depth": 1
  },
  {
    "title": "快速配置指南",
    "slug": "advanced_network_quick_guide",
    "depth": 2
  },
  {
    "title": "容器访问控制",
    "slug": "advanced_network_access_control",
    "depth": 2
  },
  {
    "title": "端口映射实现",
    "slug": "advanced_network_port_mapping",
    "depth": 2
  },
  {
    "title": "配置 docker0 网桥",
    "slug": "advanced_network_docker0",
    "depth": 2
  },
  {
    "title": "自定义网桥",
    "slug": "advanced_network_bridge",
    "depth": 2
  },
  {
    "title": "工具和示例",
    "slug": "advanced_network_example",
    "depth": 2
  },
  {
    "title": "编辑网络配置文件",
    "slug": "advanced_network_config_file",
    "depth": 2
  },
  {
    "title": "实例：创建一个点到点连接",
    "slug": "advanced_network_ptp",
    "depth": 2
  },
  {
    "title": "Docker Buildx",
    "slug": "buildx_readme",
    "depth": 1
  },
  {
    "title": "BuildKit",
    "slug": "buildx_buildkit",
    "depth": 2
  },
  {
    "title": "使用 buildx 构建镜像",
    "slug": "buildx_buildx",
    "depth": 2
  },
  {
    "title": "使用 buildx 构建多种系统架构支持的 Docker 镜像",
    "slug": "buildx_multi-arch-images",
    "depth": 2
  },
  {
    "title": "Docker Compose",
    "slug": "compose_readme",
    "depth": 1
  },
  {
    "title": "简介",
    "slug": "compose_introduction",
    "depth": 2
  },
  {
    "title": "安装与卸载",
    "slug": "compose_install",
    "depth": 2
  },
  {
    "title": "使用",
    "slug": "compose_usage",
    "depth": 2
  },
  {
    "title": "命令说明",
    "slug": "compose_commands",
    "depth": 2
  },
  {
    "title": "Compose 模板文件",
    "slug": "compose_compose_file",
    "depth": 2
  },
  {
    "title": "实战 Django",
    "slug": "compose_django",
    "depth": 2
  },
  {
    "title": "实战 Rails",
    "slug": "compose_rails",
    "depth": 2
  },
  {
    "title": "实战 WordPress",
    "slug": "compose_wordpress",
    "depth": 2
  },
  {
    "title": "实战 LNMP",
    "slug": "compose_lnmp",
    "depth": 2
  },
  {
    "title": "Swarm mode",
    "slug": "swarm_mode_readme",
    "depth": 1
  },
  {
    "title": "基本概念",
    "slug": "swarm_mode_overview",
    "depth": 2
  },
  {
    "title": "创建 Swarm 集群",
    "slug": "swarm_mode_create",
    "depth": 2
  },
  {
    "title": "部署服务",
    "slug": "swarm_mode_deploy",
    "depth": 2
  },
  {
    "title": "使用 compose 文件",
    "slug": "swarm_mode_stack",
    "depth": 2
  },
  {
    "title": "管理密钥",
    "slug": "swarm_mode_secret",
    "depth": 2
  },
  {
    "title": "管理配置信息",
    "slug": "swarm_mode_config",
    "depth": 2
  },
  {
    "title": "滚动升级",
    "slug": "swarm_mode_rolling_update",
    "depth": 2
  },
  {
    "title": "安全",
    "slug": "security_readme",
    "depth": 1
  },
  {
    "title": "内核命名空间",
    "slug": "security_kernel_ns",
    "depth": 2
  },
  {
    "title": "控制组",
    "slug": "security_control_group",
    "depth": 2
  },
  {
    "title": "服务端防护",
    "slug": "security_daemon_sec",
    "depth": 2
  },
  {
    "title": "内核能力机制",
    "slug": "security_kernel_capability",
    "depth": 2
  },
  {
    "title": "其它安全特性",
    "slug": "security_other_feature",
    "depth": 2
  },
  {
    "title": "总结",
    "slug": "security_summary",
    "depth": 2
  },
  {
    "title": "底层实现",
    "slug": "underly_readme",
    "depth": 1
  },
  {
    "title": "基本架构",
    "slug": "underly_arch",
    "depth": 2
  },
  {
    "title": "命名空间",
    "slug": "underly_namespace",
    "depth": 2
  },
  {
    "title": "控制组",
    "slug": "underly_cgroups",
    "depth": 2
  },
  {
    "title": "联合文件系统",
    "slug": "underly_ufs",
    "depth": 2
  },
  {
    "title": "容器格式",
    "slug": "underly_container_format",
    "depth": 2
  },
  {
    "title": "网络",
    "slug": "underly_network",
    "depth": 2
  },
  {
    "title": "Etcd 项目",
    "slug": "etcd_readme",
    "depth": 1
  },
  {
    "title": "简介",
    "slug": "etcd_intro",
    "depth": 2
  },
  {
    "title": "安装",
    "slug": "etcd_install",
    "depth": 2
  },
  {
    "title": "集群",
    "slug": "etcd_cluster",
    "depth": 2
  },
  {
    "title": "使用 etcdctl",
    "slug": "etcd_etcdctl",
    "depth": 2
  },
  {
    "title": "Fedora CoreOS",
    "slug": "coreos_readme",
    "depth": 1
  },
  {
    "title": "简介",
    "slug": "coreos_intro",
    "depth": 2
  },
  {
    "title": "安装",
    "slug": "coreos_install",
    "depth": 2
  },
  {
    "title": "Kubernetes - 开源容器编排引擎",
    "slug": "kubernetes_readme",
    "depth": 1
  },
  {
    "title": "简介",
    "slug": "kubernetes_intro",
    "depth": 2
  },
  {
    "title": "基本概念",
    "slug": "kubernetes_concepts",
    "depth": 2
  },
  {
    "title": "架构设计",
    "slug": "kubernetes_design",
    "depth": 2
  },
  {
    "title": "部署 Kubernetes",
    "slug": "kubernetes_setup_readme",
    "depth": 1
  },
  {
    "title": "使用 kubeadm 部署 kubernetes",
    "slug": "kubernetes_setup_kubeadm",
    "depth": 2
  },
  {
    "title": "在 Docker Desktop 使用",
    "slug": "kubernetes_setup_docker-desktop",
    "depth": 2
  },
  {
    "title": "一步步部署 kubernetes 集群",
    "slug": "kubernetes_setup_systemd",
    "depth": 2
  },
  {
    "title": "部署 Dashboard",
    "slug": "kubernetes_setup_dashboard",
    "depth": 2
  },
  {
    "title": "Kubernetes 命令行 kubectl",
    "slug": "kubernetes_kubectl_readme",
    "depth": 1
  },
  {
    "title": "容器与云计算",
    "slug": "cloud_readme",
    "depth": 1
  },
  {
    "title": "简介",
    "slug": "cloud_intro",
    "depth": 2
  },
  {
    "title": "腾讯云",
    "slug": "cloud_tencentcloud",
    "depth": 2
  },
  {
    "title": "阿里云",
    "slug": "cloud_alicloud",
    "depth": 2
  },
  {
    "title": "亚马逊云",
    "slug": "cloud_aws",
    "depth": 2
  },
  {
    "title": "小结",
    "slug": "cloud_summary",
    "depth": 2
  },
  {
    "title": "实战案例 - 操作系统",
    "slug": "cases_os_readme",
    "depth": 1
  },
  {
    "title": "Busybox",
    "slug": "cases_os_busybox",
    "depth": 2
  },
  {
    "title": "Alpine",
    "slug": "cases_os_alpine",
    "depth": 2
  },
  {
    "title": "Debian Ubuntu",
    "slug": "cases_os_debian",
    "depth": 2
  },
  {
    "title": "CentOS Fedora",
    "slug": "cases_os_centos",
    "depth": 2
  },
  {
    "title": "本章小结",
    "slug": "cases_os_summary",
    "depth": 2
  },
  {
    "title": "实战案例 - CI/CD",
    "slug": "cases_ci_readme",
    "depth": 1
  },
  {
    "title": "GitHub Actions",
    "slug": "cases_ci_actions_readme",
    "depth": 2
  },
  {
    "title": "Drone",
    "slug": "cases_ci_drone_readme",
    "depth": 2
  },
  {
    "title": "部署 Drone",
    "slug": "cases_ci_drone_install",
    "depth": 3
  },
  {
    "title": "Travis CI",
    "slug": "cases_ci_travis_readme",
    "depth": 2
  },
  {
    "title": "在 IDE 中使用 Docker",
    "slug": "ide_readme",
    "depth": 1
  },
  {
    "title": "VS Code",
    "slug": "ide_vscode",
    "depth": 2
  },
  {
    "title": "Docker 开源项目",
    "slug": "opensource_readme",
    "depth": 1
  },
  {
    "title": "LinuxKit",
    "slug": "opensource_linuxkit",
    "depth": 2
  },
  {
    "title": "podman - 下一代 Linux 容器工具",
    "slug": "podman_readme",
    "depth": 1
  },
  {
    "title": "附录",
    "slug": "appendix_readme",
    "depth": 1
  },
  {
    "title": "附录一：常见问题总结",
    "slug": "appendix_faq_readme",
    "depth": 2
  },
  {
    "title": "附录二：热门镜像介绍",
    "slug": "appendix_repo_readme",
    "depth": 2
  },
  {
    "title": "Ubuntu",
    "slug": "appendix_repo_ubuntu",
    "depth": 3
  },
  {
    "title": "CentOS",
    "slug": "appendix_repo_centos",
    "depth": 3
  },
  {
    "title": "Nginx",
    "slug": "appendix_repo_nginx",
    "depth": 3
  },
  {
    "title": "PHP",
    "slug": "appendix_repo_php",
    "depth": 3
  },
  {
    "title": "Node.js",
    "slug": "appendix_repo_nodejs",
    "depth": 3
  },
  {
    "title": "MySQL",
    "slug": "appendix_repo_mysql",
    "depth": 3
  },
  {
    "title": "WordPress",
    "slug": "appendix_repo_wordpress",
    "depth": 3
  },
  {
    "title": "MongoDB",
    "slug": "appendix_repo_mongodb",
    "depth": 3
  },
  {
    "title": "Redis",
    "slug": "appendix_repo_redis",
    "depth": 3
  },
  {
    "title": "附录三：Docker 命令查询",
    "slug": "appendix_command_readme",
    "depth": 2
  },
  {
    "title": "客户端命令 - docker",
    "slug": "appendix_command_docker",
    "depth": 3
  },
  {
    "title": "服务端命令 - dockerd",
    "slug": "appendix_command_dockerd",
    "depth": 3
  },
  {
    "title": "附录四：Dockerfile 最佳实践",
    "slug": "appendix_best_practices",
    "depth": 2
  },
  {
    "title": "附录五：如何调试 Docker",
    "slug": "appendix_debug",
    "depth": 2
  },
  {
    "title": "附录六：资源链接",
    "slug": "appendix_resources",
    "depth": 2
  },
  {
    "title": "归档",
    "slug": "archive_readme",
    "depth": 1
  },
  {
    "title": "Mesos - 优秀的集群资源调度平台",
    "slug": "mesos_readme",
    "depth": 2
  },
  {
    "title": "Mesos 简介",
    "slug": "mesos_intro",
    "depth": 3
  },
  {
    "title": "安装与使用",
    "slug": "mesos_installation",
    "depth": 3
  },
  {
    "title": "原理与架构",
    "slug": "mesos_architecture",
    "depth": 3
  },
  {
    "title": "Mesos 配置项解析",
    "slug": "mesos_configuration",
    "depth": 3
  },
  {
    "title": "日志与监控",
    "slug": "mesos_monitor",
    "depth": 3
  },
  {
    "title": "常见应用框架",
    "slug": "mesos_framework",
    "depth": 3
  },
  {
    "title": "本章小结",
    "slug": "mesos_summary",
    "depth": 3
  },
  {
    "title": "Docker Machine",
    "slug": "machine_readme",
    "depth": 2
  },
  {
    "title": "安装",
    "slug": "machine_install",
    "depth": 3
  },
  {
    "title": "使用",
    "slug": "machine_usage",
    "depth": 3
  },
  {
    "title": "Docker Swarm",
    "slug": "swarm_readme",
    "depth": 2
  }
]